<?xml version="1.0" encoding="utf-8" standalone="yes" ?>
<T3locallang>
	<meta type="array">
		<type>database</type>
		<description>Language labels for database tables/fields belonging to extension 'felogin'</description>
	</meta>
	<data type="array">
		<languageKey index="default" type="array">
			<label index="tt_content.CType_pi1">Website User Login</label>
			<label index="felogin_redirectPid">Redirect at Login to Page (felogin):</label>
			<label index="tt_content.pi_flexform.general_header">General Header:</label>
			<label index="tt_content.pi_flexform.general_message">General Message:</label>
			<label index="tt_content.pi_flexform.redirect_header">Redirect Header:</label>
			<label index="tt_content.pi_flexform.redirect_message">Redirect Message:</label>
			<label index="tt_content.pi_flexform.welcome_header">Welcome Header:</label>
			<label index="tt_content.pi_flexform.welcome_message">Welcome Message:</label>
			<label index="tt_content.pi_flexform.success_header">Login Success Header:</label>
			<label index="tt_content.pi_flexform.success_message">Login Success Message:</label>
			<label index="tt_content.pi_flexform.error_header">Login Error Header:</label>
			<label index="tt_content.pi_flexform.error_message">Login Error Message:</label>
			<label index="tt_content.pi_flexform.status_header">Status Display Header:</label>
			<label index="tt_content.pi_flexform.status_message">Status Display Message:</label>
			<label index="tt_content.pi_flexform.logout_header">Logout Header:</label>
			<label index="tt_content.pi_flexform.logout_message">Logout Message:</label>
			<label index="tt_content.pi_flexform.forgot_header">Forgot Password Header:</label>
			<label index="tt_content.pi_flexform.forgot_message">Forgot Password Message:</label>
			<label index="tt_content.pi_flexform.sheet_general">General</label>
			<label index="tt_content.pi_flexform.sheet_redirect">Redirect Options</label>
			<label index="tt_content.pi_flexform.sheet_messages">Messages</label>
			<label index="tt_content.pi_flexform.show_forgot_password">Show &quot;Forgot password?&quot; link:</label>
			<label index="tt_content.pi_flexform.show_permalogin">Show &quot;Stay logged in&quot; checkbox (if switched on for the installation):</label>
			<label index="tt_content.pi_flexform.groupSelectmode">FE group select mode:</label>
			<label index="tt_content.pi_flexform.groupSelectmode_showAll">Show all</label>
			<label index="tt_content.pi_flexform.groupSelectmode_showSelected">Show selected</label>
			<label index="tt_content.pi_flexform.groupSelectmode_DontShowSelected">Dont show selected</label>
			<label index="tt_content.pi_flexform.groupSelectmode_FromTS">(from Typoscript)</label>
			<label index="tt_content.pi_flexform.groupSelection">FE group selection:</label>
			<label index="tt_content.pi_flexform.groupSelection_noGroup">no group</label>
			<label index="tt_content.pi_flexform.field_manualOrder">Using fieldlists below:</label>
			<label index="tt_content.pi_flexform.field_orderList">User Fields/list:</label>
			<label index="tt_content.pi_flexform.field_orderDetails">User Fields/details:</label>
			<label index="tt_content.pi_flexform.redirectMode">Redirect Mode (you have to choose the options, without defined Mode there is no redirect):</label>
			<label index="tt_content.pi_flexform.redirectMode.I.0">defined by Usergroup Record</label>
			<label index="tt_content.pi_flexform.redirectMode.I.1">defined by User Record</label>
			<label index="tt_content.pi_flexform.redirectMode.I.2">after Login (TS or Flexform)</label>
			<label index="tt_content.pi_flexform.redirectMode.I.3">after Logout (TS or Flexform)</label>
			<label index="tt_content.pi_flexform.redirectMode.I.4">after Login Error (TS or Flexform)</label>
			<label index="tt_content.pi_flexform.redirectMode.I.5">defined by GET/POST-Vars</label>
			<label index="tt_content.pi_flexform.redirectMode.I.6">defined by Referrer</label>
			<label index="tt_content.pi_flexform.redirectMode.I.7">defined by Domain entries</label>
			<label index="tt_content.pi_flexform.redirectFirstMethod">Use the first mode found:</label>
			<label index="tt_content.pi_flexform.redirectDisable">Disable redirect:</label>
			<label index="tt_content.pi_flexform.redirectPageLogin">After successful login redirect to page:</label>
			<label index="tt_content.pi_flexform.redirectPageLoginError">After login with error redirect to page:</label>
			<label index="tt_content.pi_flexform.redirectPageLogout">After logout redirect to page:</label>
			<label index="tt_content.pi_flexform.template_file">Template file:</label>
		</languageKey>
		
		<languageKey index="dk" type="array">
			<label index="tt_content.pi_flexform.header">Overskrift:</label>
			<label index="tt_content.pi_flexform.message">Tekst:</label>
			<label index="tt_content.pi_flexform.sheet_general">Generelle valg</label>
			<label index="tt_content.pi_flexform.sheet_welcome">Velkomst</label>
			<label index="tt_content.pi_flexform.sheet_success">Login Succes</label>
			<label index="tt_content.pi_flexform.sheet_error">Login Fejl</label>
			<label index="tt_content.pi_flexform.sheet_status">Status</label>
			<label index="tt_content.pi_flexform.sheet_logout">Logout</label>
			<label index="tt_content.pi_flexform.show_forgot_password">Vis &quot;Glemt password?&quot; link:</label>
			<label index="tt_content.pi_flexform.template_file">Skabelon fil</label>
		</languageKey>
		<languageKey index="de" type="array">
			<label index="tt_content.pi_flexform.header">Überschrift:</label>
			<label index="tt_content.pi_flexform.message">Nachricht:</label>
			<label index="tt_content.pi_flexform.sheet_general">Allgemein</label>
			<label index="tt_content.pi_flexform.sheet_welcome">Willkommen</label>
			<label index="tt_content.pi_flexform.sheet_success">Erfolgreich angemeldet</label>
			<label index="tt_content.pi_flexform.sheet_error">Anmeldefehler</label>
			<label index="tt_content.pi_flexform.sheet_status">Status</label>
			<label index="tt_content.pi_flexform.sheet_logout">Abmelden</label>
			<label index="tt_content.pi_flexform.show_forgot_password">&quot;Passwort vergessen?&quot; Link anzeigen:</label>
			<label index="tt_content.pi_flexform.show_permalogin">&quot;Eingeloggt bleiben&quot; checkbox anzeigen (wenn auf dem System verfügbar:</label>
			<label index="tt_content.pi_flexform.groupSelectmode">FE-Gruppen Auswahlmodus:</label>
			<label index="tt_content.pi_flexform.groupSelectmode_showAll">Alle anzeigen</label>
			<label index="tt_content.pi_flexform.groupSelectmode_showSelected">Nur die Ausgewählten anzeigen</label>
			<label index="tt_content.pi_flexform.groupSelectmode_DontShowSelected">Die Ausgewählten NICHT anzeigen</label>
			<label index="tt_content.pi_flexform.groupSelectmode_FromTS">(gemäss Typoscript)</label>
			<label index="tt_content.pi_flexform.groupSelection">FE-Gruppen Auswahl:</label>
			<label index="tt_content.pi_flexform.groupSelection_noGroup">in keiner Gruppe einsortiert</label>
			<label index="tt_content.pi_flexform.field_manualOrder">Folgende Felder benutzen:</label>
			<label index="tt_content.pi_flexform.field_orderList">Listenansicht:</label>
			<label index="tt_content.pi_flexform.field_orderDetails">Detailansicht:</label>
			<label index="tt_content.pi_flexform.redirectPageLogin">Nach erfolgreichem Login auf folgende Seite weiterleiten:</label>
			<label index="tt_content.pi_flexform.template_file">Template:</label>
			<label index="felogin_redirPid">Beim Login weiterleiten zur Seite...</label>
		</languageKey>
		<languageKey index="no" type="array">
			<label index="tt_content.pi_flexform.header">Overskrift:</label>
			<label index="tt_content.pi_flexform.message">Tekst:</label>
			<label index="tt_content.pi_flexform.sheet_general">Generelle valg</label>
			<label index="tt_content.pi_flexform.sheet_welcome">Velkomstmelding</label>
			<label index="tt_content.pi_flexform.sheet_success">Vellykket innlogging</label>
			<label index="tt_content.pi_flexform.sheet_error">Feil ved innlogging</label>
			<label index="tt_content.pi_flexform.sheet_status">Status</label>
			<label index="tt_content.pi_flexform.sheet_logout">Logg ut</label>
			<label index="tt_content.pi_flexform.show_forgot_password">Vis &quot;Glemt passordet?&quot;-lenke</label>
			<label index="tt_content.pi_flexform.field_manualOrder">Bruk feltlisten under:</label>
			<label index="tt_content.pi_flexform.field_orderList">Brukerfelter/liste:</label>
			<label index="tt_content.pi_flexform.field_orderDetails">Brukerfelter/detaljer:</label>
			<label index="tt_content.pi_flexform.template_file">Malfil</label>
		</languageKey>
		<languageKey index="it" type="array">
			<label index="tt_content.pi_flexform.header">Intestazione:</label>
			<label index="tt_content.pi_flexform.message">Messaggio:</label>
			<label index="tt_content.pi_flexform.sheet_general">Generale:</label>
			<label index="tt_content.pi_flexform.sheet_welcome">Benvenuto</label>
			<label index="tt_content.pi_flexform.sheet_success">Login avvenuto</label>
			<label index="tt_content.pi_flexform.sheet_error">Errore di Login</label>
			<label index="tt_content.pi_flexform.sheet_status">Stato</label>
			<label index="tt_content.pi_flexform.sheet_logout">Logout</label>
			<label index="tt_content.pi_flexform.show_forgot_password">Mostra link &quot;Dimenticato la password?&quot;:</label>
			<label index="tt_content.pi_flexform.field_manualOrder">Usa i campi sottostanti:</label>
			<label index="tt_content.pi_flexform.field_orderList">Campi Utente/lista:</label>
			<label index="tt_content.pi_flexform.field_orderDetails">Campi Utente/dettagli:</label>
			<label index="felogin_redirPid">Carica la pagina (al login)</label>
		</languageKey>
		<languageKey index="fr" type="array">
			<label index="tt_content.pi_flexform.header">Titre</label>
			<label index="tt_content.pi_flexform.message">Message</label>
			<label index="tt_content.pi_flexform.sheet_general">Général</label>
			<label index="tt_content.pi_flexform.sheet_welcome">Bienvenue</label>
			<label index="tt_content.pi_flexform.sheet_success">Succès</label>
			<label index="tt_content.pi_flexform.sheet_error">Erreur</label>
			<label index="tt_content.pi_flexform.sheet_status">État</label>
			<label index="tt_content.pi_flexform.sheet_logout">Déconnexion</label>
			<label index="tt_content.pi_flexform.show_forgot_password">Affiché le lien &quot;Mot de passe oublié?&quot;</label>
			<label index="tt_content.pi_flexform.field_manualOrder">Utiliser les champs suivant:</label>
			<label index="tt_content.pi_flexform.field_orderList">Champs (liste)</label>
			<label index="tt_content.pi_flexform.field_orderDetails">Champs (détails)</label>
		</languageKey>
		<languageKey index="es" type="array">
			<label index="tt_content.pi_flexform.template_file">Fichero de plantilla</label>
		</languageKey>
		<languageKey index="nl" type="array">
			<label index="tt_content.pi_flexform.header">Kop:</label>
			<label index="tt_content.pi_flexform.message">Bericht:</label>
			<label index="tt_content.pi_flexform.sheet_general">Algemeen</label>
			<label index="tt_content.pi_flexform.sheet_welcome">Welkom</label>
			<label index="tt_content.pi_flexform.sheet_success">Inloggen gelukt</label>
			<label index="tt_content.pi_flexform.sheet_error">Fout bij het inloggen</label>
			<label index="tt_content.pi_flexform.sheet_status">Status</label>
			<label index="tt_content.pi_flexform.sheet_logout">Uitloggen</label>
			<label index="tt_content.pi_flexform.show_forgot_password">Toon &quot;Password vergeten?&quot; link:</label>
			<label index="tt_content.pi_flexform.template_file">Sjabloon bestand</label>
		</languageKey>
		<languageKey index="cz" type="array">
			<label index="tt_content.pi_flexform.header">Nadpis</label>
			<label index="tt_content.pi_flexform.message">Zpráva:</label>
			<label index="tt_content.pi_flexform.sheet_general">Obecné</label>
			<label index="tt_content.pi_flexform.sheet_welcome">Vítejte</label>
			<label index="tt_content.pi_flexform.sheet_success">Úspěšné přihlášení</label>
			<label index="tt_content.pi_flexform.sheet_error">Chyba přihlášení</label>
			<label index="tt_content.pi_flexform.sheet_status">Stav</label>
			<label index="tt_content.pi_flexform.sheet_logout">Odhlášení</label>
			<label index="tt_content.pi_flexform.show_forgot_password">Zobrazovat odkaz &quot;Zapoměli jste své heslo&quot;?</label>
			<label index="tt_content.pi_flexform.template_file">Soubor šablony</label>
		</languageKey>
		<languageKey index="pl" type="array">
			<label index="tt_content.pi_flexform.header">Nagłówek:</label>
			<label index="tt_content.pi_flexform.message">Wiadomość:</label>
			<label index="tt_content.pi_flexform.sheet_general">Ogólne</label>
			<label index="tt_content.pi_flexform.sheet_welcome">Powitanie</label>
			<label index="tt_content.pi_flexform.sheet_success">Udane logowanie</label>
			<label index="tt_content.pi_flexform.sheet_error">Błędne logowanie</label>
			<label index="tt_content.pi_flexform.sheet_status">Status</label>
			<label index="tt_content.pi_flexform.sheet_logout">Wylogowanie</label>
			<label index="tt_content.pi_flexform.show_forgot_password">Pokazuj odnośnik &quot;zapomniałem hasło&quot;:</label>
			<label index="tt_content.pi_flexform.field_manualOrder">Użycie listy pól poniżej:</label>
			<label index="tt_content.pi_flexform.field_orderList">Pola użytkownika/lista:</label>
			<label index="tt_content.pi_flexform.field_orderDetails">Pola użytkownika/szczegóły:</label>
			<label index="felogin_redirPid">Przekieruj po zalogowaniu do strony:</label>
		</languageKey>
		<languageKey index="si" type="array">
		</languageKey>
		<languageKey index="fi" type="array">
			<label index="tt_content.pi_flexform.header">Otsikko:</label>
			<label index="tt_content.pi_flexform.message">Viesti</label>
			<label index="tt_content.pi_flexform.sheet_general">Yleistä</label>
			<label index="tt_content.pi_flexform.sheet_welcome">Tervetulotoivotus</label>
			<label index="tt_content.pi_flexform.sheet_success">Onnistunut sisäänkirjoitus</label>
			<label index="tt_content.pi_flexform.sheet_error">Epäonnistunut sisäänkirjoitus</label>
			<label index="tt_content.pi_flexform.sheet_status">Tila</label>
			<label index="tt_content.pi_flexform.sheet_logout">Ulos kirjoittautuminen</label>
			<label index="tt_content.pi_flexform.show_forgot_password">Näytä &quot;Unohditko salasanasi ?&quot; linkki:</label>
			<label index="tt_content.pi_flexform.field_manualOrder">Käytetään allaolevaa tietolistaa:</label>
			<label index="tt_content.pi_flexform.field_orderList">Käyttäjän tiedot/lista:</label>
			<label index="tt_content.pi_flexform.field_orderDetails">Käyttäjän tiedot/tarkat tiedot:</label>
			<label index="felogin_redirPid">Edelleen ohjaus loginissa sivulle:</label>
		</languageKey>
		<languageKey index="tr" type="array">
			<label index="tt_content.pi_flexform.header">Başlık:</label>
			<label index="tt_content.pi_flexform.message">Mesaj:</label>
			<label index="tt_content.pi_flexform.sheet_general">Genel</label>
			<label index="tt_content.pi_flexform.sheet_welcome">Hoşgeldin</label>
			<label index="tt_content.pi_flexform.sheet_success">Oturum başarıyla açıldı</label>
			<label index="tt_content.pi_flexform.sheet_error">Oturum açmada hata</label>
			<label index="tt_content.pi_flexform.sheet_status">Statü</label>
			<label index="tt_content.pi_flexform.sheet_logout">Oturumu kapat</label>
			<label index="tt_content.pi_flexform.show_forgot_password">'Parola kayıp?' linkini göster:</label>
			<label index="tt_content.pi_flexform.field_manualOrder">Altdaki alan listelerini kullan:</label>
			<label index="tt_content.pi_flexform.field_orderList">Liste görüntüsü</label>
			<label index="tt_content.pi_flexform.field_orderDetails">Detaylı görüntü</label>
		</languageKey>
		<languageKey index="se" type="array">
			<label index="felogin_redirPid">Vidareskicka vid inloggning till sidan:</label>
		</languageKey>
		<languageKey index="pt" type="array">
		</languageKey>
		<languageKey index="ru" type="array">
			<label index="tt_content.pi_flexform.header">Заголовок:</label>
			<label index="tt_content.pi_flexform.message">Сообщение:</label>
			<label index="tt_content.pi_flexform.sheet_general">Общие</label>
			<label index="tt_content.pi_flexform.sheet_welcome">Добро пожаловать!</label>
			<label index="tt_content.pi_flexform.sheet_success">Успешный вход</label>
			<label index="tt_content.pi_flexform.sheet_error">Ошибка входа</label>
			<label index="tt_content.pi_flexform.sheet_status">Статус</label>
			<label index="tt_content.pi_flexform.sheet_logout">Выход</label>
			<label index="tt_content.pi_flexform.show_forgot_password">Показывать ссылку &quot;Забыли пароль?&quot;</label>
			<label index="tt_content.pi_flexform.field_manualOrder">Используя список полей внизу:</label>
			<label index="tt_content.pi_flexform.field_orderList">Поля в режиме списка пользователей:</label>
			<label index="tt_content.pi_flexform.field_orderDetails">Поля в режиме деталей пользователя:</label>
		</languageKey>
		<languageKey index="ro" type="array">
		</languageKey>
		<languageKey index="ch" type="array">
		</languageKey>
		<languageKey index="sk" type="array">
		</languageKey>
		<languageKey index="lt" type="array">
		</languageKey>
		<languageKey index="is" type="array">
		</languageKey>
		<languageKey index="hr" type="array">
			<label index="tt_content.pi_flexform.header">Zaglavlje:</label>
			<label index="tt_content.pi_flexform.message">Poruka:</label>
			<label index="tt_content.pi_flexform.sheet_general">Općenito</label>
			<label index="tt_content.pi_flexform.sheet_welcome">Dobrodošli</label>
			<label index="tt_content.pi_flexform.sheet_success">Prijava uspješna</label>
			<label index="tt_content.pi_flexform.sheet_error">Greška pri prijavi</label>
			<label index="tt_content.pi_flexform.sheet_status">Status</label>
			<label index="tt_content.pi_flexform.sheet_logout">Odjava</label>
			<label index="tt_content.pi_flexform.show_forgot_password">Prikaži &quot;Zaboravljena lozinka?&quot; link:</label>
			<label index="tt_content.pi_flexform.field_manualOrder">Koristeći niže navedena polja:</label>
			<label index="tt_content.pi_flexform.field_orderList">Korisnička Polja/popis:</label>
			<label index="tt_content.pi_flexform.field_orderDetails">Korisnička Polja/detalji:</label>
		</languageKey>
		<languageKey index="hu" type="array">
		</languageKey>
		<languageKey index="gl" type="array">
		</languageKey>
		<languageKey index="th" type="array">
		</languageKey>
		<languageKey index="gr" type="array">
		</languageKey>
		<languageKey index="hk" type="array">
		</languageKey>
		<languageKey index="eu" type="array">
		</languageKey>
		<languageKey index="bg" type="array">
		</languageKey>
		<languageKey index="br" type="array">
			<label index="tt_content.pi_flexform.header">Cabeçalho:</label>
			<label index="tt_content.pi_flexform.message">Mensagem:</label>
			<label index="tt_content.pi_flexform.sheet_general">Geral</label>
			<label index="tt_content.pi_flexform.sheet_welcome">Bem-vindo</label>
			<label index="tt_content.pi_flexform.sheet_success">Identificação com Sucesso</label>
			<label index="tt_content.pi_flexform.sheet_error">Erro de Identificação</label>
			<label index="tt_content.pi_flexform.sheet_status">Situação</label>
			<label index="tt_content.pi_flexform.sheet_logout">Encerrar</label>
			<label index="tt_content.pi_flexform.show_forgot_password">Exibir o link &quot;Esqueci minha senha?&quot;:</label>
			<label index="tt_content.pi_flexform.field_manualOrder">Utilizando os campos abaixo:</label>
			<label index="tt_content.pi_flexform.field_orderList">Campos de Usuário/Lista:</label>
			<label index="tt_content.pi_flexform.field_orderDetails">Campos de Usuário/Detalhes:</label>
			<label index="felogin_redirPid">Ao logar, redirecionar para Página:</label>
		</languageKey>
		<languageKey index="et" type="array">
		</languageKey>
		<languageKey index="ar" type="array">
		</languageKey>
		<languageKey index="he" type="array">
		</languageKey>
		<languageKey index="ua" type="array">
		</languageKey>
		<languageKey index="lv" type="array">
		</languageKey>
		<languageKey index="jp" type="array">
		</languageKey>
		<languageKey index="vn" type="array">
		</languageKey>
		<languageKey index="ca" type="array">
		</languageKey>
		<languageKey index="ba" type="array">
		</languageKey>
		<languageKey index="kr" type="array">
		</languageKey>
		<languageKey index="eo" type="array">
		</languageKey>
		<languageKey index="my" type="array">
		</languageKey>
		<languageKey index="hi" type="array">
		</languageKey>
	</data>
</T3locallang>
