<?xml version="1.0" encoding="utf-8" standalone="yes" ?>
<T3locallang>
    <meta type="array">
        <description>CSH labels</description>
        <type>CSH</type>
        <csh_table>openid</csh_table>
        <fileId>EXT:openid/locallang_csh.xml</fileId>
        <labelContext type="array">
        </labelContext>
    </meta>
    <data type="array">
        <languageKey index="default" type="array">
            <label index="tx_openid_openid.description">OpenID identifier</label>
            <label index="tx_openid_openid.details">This field contains option OpenID identifier. If the field is not empty, users can login to the system using their OpenID identifier.</label>
            <label index="tx_openid_openid.seeAlso">http://openid.net/</label>
            <label index="tx_openid_change_allowed.description">If this setting is active, users can change their own OpenID identifier using the setup module.</label>
        </languageKey>
    </data>
</T3locallang>