<?xml version="1.0" encoding="utf-8" standalone="yes" ?>
<T3locallang>
	<meta type="array">
		<description>Labels for Definition List plugin of htmlArea RTE</description>
		<type>module</type>
	</meta>
	<data type="array">
		<languageKey index="default" type="array">
			<label index="Indent-Tooltip">Increase indent</label>
			<label index="Indent-helpText">Increases text indentation</label>
			<label index="Outdent-Tooltip">Reduce indent</label>
			<label index="Outdent-helpText">Reduces text indentation</label>
			<label index="DefinitionList-Tooltip">Definition list</label>
			<label index="DefinitionList-helpText">Makes a definition list from the current selection</label>
			<label index="DefinitionItem-Tooltip">Toggle term and definition</label>
			<label index="DefinitionItem-helpText">Toggles term and definition elements</label>
			<label index="No block">No block format</label>
			<label index="Remove block">Remove block format</label>
			<label index="Technische Universitat Ilmenau">Technische Universität Ilmenau</label>
		</languageKey>
	</data>
	<orig_hash type="array">
		<languageKey index="default" type="array">
		</languageKey>
	</orig_hash>
	<orig_text type="array">
		<languageKey index="default" type="array">
		</languageKey>
	</orig_text>
</T3locallang>